micro_ci/__init__.py
micro_ci/main.py
micro_ci-0.1.2.dist-info/LICENSE
micro_ci-0.1.2.dist-info/METADATA
micro_ci-0.1.2.dist-info/WHEEL
micro_ci-0.1.2.dist-info/entry_points.txt
micro_ci-0.1.2.dist-info/top_level.txt
micro_ci-0.1.2.dist-info/RECORD
