Metadata-Version: 2.1
Name: micro-ci
Version: 0.1.2
Summary: Micro-CI: A minimalist runner for GitLab CI configurations.
Home-page: https://gitlab.com/gauss-ml-open/micro-ci
Author: Edgar Klenske
Author-email: edgar.klenske@gauss-ml.com
License: UNKNOWN
Keywords: development
Platform: UNKNOWN
Classifier: Development Status :: 3 - Alpha
Classifier: Intended Audience :: Developers
Classifier: Topic :: Software Development :: Build Tools
Classifier: License :: OSI Approved :: BSD License
Classifier: Programming Language :: Python :: 3
Classifier: Programming Language :: Python :: 3.5
Classifier: Programming Language :: Python :: 3.6
Classifier: Programming Language :: Python :: 3.7
Classifier: Programming Language :: Python :: 3.8
Classifier: Programming Language :: Python :: 3 :: Only
Requires-Python: >=3.5, <4
Requires-Dist: pyyaml
Provides-Extra: dev
Requires-Dist: black ; extra == 'dev'
Requires-Dist: flake8 ; extra == 'dev'
Requires-Dist: mypy ; extra == 'dev'
Requires-Dist: pylint ; extra == 'dev'
Requires-Dist: rope ; extra == 'dev'
Provides-Extra: test
Requires-Dist: flaky ; extra == 'test'
Requires-Dist: pytest ; extra == 'test'
Requires-Dist: pytest-cov ; extra == 'test'
